Metadata-Version: 2.1
Name: autoreduce-scripts
Version: 22.0.0.dev44
Summary: ISIS Autoreduce helper scripts
License: GNU General Public License
Project-URL: Repository, https://github.com/autoreduction/scripts
Project-URL: Wiki, https://github.com/autoreduction/queue-processor/wiki
Classifier: Framework :: Django
Classifier: Programming Language :: Python :: 3
License-File: LICENSE.txt
Requires-Dist: autoreduce-db (==22.0.0.dev37)
Requires-Dist: autoreduce-utils (==22.0.0.dev23)
Requires-Dist: Django
Requires-Dist: fire (==0.4.0)
Requires-Dist: h5py (==3.7.0)
Requires-Dist: GitPython
Requires-Dist: stomp.py
